{
  "angry": [
    "irritado",
    "irado",
    "enraivecido",
    "furioso",
    "enfurecido",
    "encolerizado",
    "colérico",
    "enervado",
    "fulo",
    "furibundo",
    "enfuriado",
    "exasperado",
    "danado",
    "agastado",
    "embravecido",
    "apoquentado",
    "abespinhado",
    "arrenegado",
    "irritada",
    "irada",
    "enraivecida",
    "furiosa",
    "enfurecida",
    "encolerizada",
    "colérica",
    "enervada",
    "fula",
    "furibunda",
    "enfuriada",
    "exasperada",
    "danada",
    "agastada",
    "embravecida",
    "apoquentada",
    "abespinhada",
    "arrenegada"
  ],
  "confused": [
    "caótico",
    "baralhado",
    "desarranjado",
    "desalinhado",
    "bagunçado",
    "desconexo",
    "desordenado",
    "desorganizado",
    "emaranhado",
    "embaralhado",
    "intrincado",
    "meândrico",
    "meandroso",
    "misturado",
    "revolto",
    "sinuoso",
    "ambíguo",
    "arrevesado",
    "complexo",
    "complicado",
    "duvidoso",
    "embrulhado",
    "equívoco",
    "impreciso",
    "incompreensível",
    "indefinido",
    "indelineável",
    "indistinguível",
    "indistinto",
    "inexato",
    "inextricável",
    "ininteligente",
    "labiríntico",
    "nebuloso",
    "obscuro",
    "túrbido",
    "vago",
    "atarantado",
    "alterado",
    "atônito",
    "atrapalhado",
    "confundido",
    "desconcertado",
    "desorientado",
    "embaraçado",
    "enleado",
    "perplexo",
    "perturbado",
    "transtornado",
    "caótica",
    "baralhada",
    "desarranjada",
    "desalinhada",
    "bagunçada",
    "desconexa",
    " desordenada",
    "desorganizada",
    "emaranhada",
    "embaralhada",
    "intrincada",
    "meândrica",
    "meandrosa",
    "misturada",
    "revolta",
    "sinuosa",
    "ambígua",
    "arrevesada",
    "complexa",
    "complicada",
    "duvidosa",
    "embrulhada",
    "equívoca",
    "imprecisa",
    "indefinida",
    "indistinta",
    "inexata",
    "ininteligente",
    "labiríntica",
    "nebulosa",
    "obscura",
    "túrbida",
    "vaga",
    " atarantada",
    "alterada",
    "atônita",
    "atrapalhada",
    "confundida",
    "desconcertada",
    "desorientada",
    "embaraçada",
    "enleada",
    "perplexa",
    "perturbada",
    "transtornada"
  ],
  "embarrassed": [
    "tímido",
    "inibido",
    "acanhado",
    "encabulado",
    "introvertido",
    "recatado",
    "retraído",
    "encolhido",
    "embaraçado",
    "constrangido",
    "atrapalhado",
    "sem jeito",
    "corado",
    "ruborizado",
    "pejoso",
    "pudico",
    "encalistrado",
    "canhestro",
    "bisonho",
    "tímida",
    "inibida",
    "acanhada",
    "encabulada",
    "introvertida",
    "recatada",
    "retraída",
    "encolhida",
    "embaraçada",
    "constrangida",
    "atrapalhada",
    "corada",
    "ruborizada",
    "pejosa",
    "pudica",
    "encalistrada",
    "canhestra",
    "bisonha",
    "humilhado",
    "desonrado",
    "aviltado",
    "depreciado",
    "desvalorizado",
    "diminuído",
    "rebaixado",
    "menosprezado",
    "ultrajado",
    "vexado",
    "ridicularizado",
    "espezinhado",
    "acabrunhado",
    "achincalhado",
    "menoscabado",
    "humilhada",
    "desonrada",
    "aviltada",
    "depreciada",
    "desvalorizada",
    "diminuída",
    "rebaixada",
    "menosprezada",
    "ultrajada",
    "vexada",
    "ridicularizada",
    "espezinhada",
    "acabrunhada",
    "achincalhada",
    "menoscabada"
  ],
  "nervous": [
    "irritado",
    "agitado",
    "exasperado",
    "impaciente",
    "agastado",
    "agastadiço",
    "abalado",
    "inquieto",
    "ansioso",
    "angustiado",
    "alvoroçado",
    "estressado",
    "desequilibrado",
    "descontrolado",
    "aflito",
    "irritada",
    "agitada",
    "exasperada",
    "impaciente",
    "agastada",
    "agastadiça",
    "abalada",
    "inquieta",
    "ansiosa",
    "angustiada",
    "alvoroçada",
    "estressada",
    "desequilibrada",
    "descontrolada",
    "aflita",
    "rápido",
    "enérgico",
    "vigoroso",
    "frenético",
    "sôfrego",
    "rápida",
    "enérgica",
    "vigorosa",
    "frenética",
    "sôfrega",
    "nervosismo",
    "enervamento",
    "irritabilidade",
    "irritação",
    "ansiedade",
    "tensão",
    "excitação",
    "agitação",
    "desassossego",
    "inquietação",
    "impaciência",
    "apoquentação",
    "ralação",
    "desinquietação",
    "nervosidade",
    "nervosia",
    "neurastenia",
    "estresse",
    "stress",
    "mau humor"
  ],
  "happy": [
    "alegre",
    "contente",
    "animado",
    "divertido",
    "eufórico",
    "folgado",
    "festo",
    "faceiro",
    "jovial",
    "aprazível",
    "fagueiro",
    "álacre",
    "exultante",
    "doce",
    "ledo",
    "jubiloso",
    "jucundo",
    "prazenteiro",
    "lépido",
    "prazeroso",
    "radiante",
    "hilariante",
    "hilário",
    "realizado",
    "hílare",
    "satisfeito",
    "sorridente",
    "animada",
    "divertida",
    "eufórica",
    "folgada",
    "festiva",
    "faceira",
    "fagueira",
    "leda",
    "jubilosa",
    "jucunda",
    "prazenteira",
    "lépida",
    "prazerosa",
    "hilária",
    "satisfeita",
    "sortudo",
    "felizardo",
    "afortunado",
    "pé-quente",
    "bem-afortunado",
    "beato",
    "abortado",
    "bem-fadado",
    "fortunado",
    "fortunoso",
    "agraciado",
    "lanzudo",
    "empelicado",
    "peludo",
    "sortuda",
    "felizarda",
    "afortunada",
    "bem-afortunada",
    "beata",
    "abortada",
    "bem-fadada",
    "fortunada",
    "fortunosa",
    "agraciada",
    "lanzuda",
    "empelicada",
    "peluda",
    "animador",
    "encorajador",
    "estimulante",
    "incentivador",
    "empolgante",
    "esperançoso",
    "benéfico",
    "benfazejo",
    "benigno",
    "auspicioso",
    "alvissareiro",
    "alentador",
    "encorajante",
    "incentivante",
    "florescente",
    "promissor",
    "animadora",
    "encorajadora",
    "incentivadora",
    "esperançosa",
    "benéfica",
    "benfazeja",
    "benigna",
    "auspiciosa",
    "alvissareira",
    "alentadora",
    "promissora",
    "abençoado",
    "protegido",
    "louvado",
    "bendito",
    "bem-aventurado",
    "bento",
    "santificado",
    "venturoso",
    "ditoso",
    "abençoada",
    "protegida",
    "louvada",
    "bendita",
    "bem-aventurada",
    "benta",
    "santificada",
    "venturosa",
    "ditosa",
    "conveniente",
    "adequado",
    "bom",
    "propício",
    "favorável",
    "acertado",
    "apropriado",
    "devido",
    "exato",
    "oportuno",
    "ótimo",
    "próprio",
    "fasto",
    "fausto",
    "providencial",
    "vantajoso",
    "adequada",
    "boa",
    "propícia",
    "acertada",
    "apropriada",
    "devida",
    "exata",
    "oportuna",
    "ótima",
    "própria",
    "fastosa",
    "fausta",
    "vantajosa",
    "próspero",
    "próspera",
    "tranquilo",
    "tranquila"
  ],
  "sad": [
    "infeliz",
    "tristonho",
    "melancólico",
    "taciturno",
    "deprimido",
    "desanimado",
    "soturno",
    "sorumbático",
    "desgostoso",
    "descontente",
    "macambúzio",
    "lamentoso",
    "lastimoso",
    "jururu",
    "borocoxô",
    "choroso",
    "lacrimoso",
    "desalegre",
    "magoado",
    "malcontente",
    "injucundo",
    "mofino",
    "merencório",
    "prostrado",
    "tristonha",
    "melancólica",
    "taciturna",
    "deprimida",
    "desanimada",
    "soturna",
    "sorumbática",
    "desgostosa",
    "macambúzia",
    "lamentosa",
    "lastimosa",
    "chorosa",
    "lacrimosa",
    "magoada",
    "injucunda",
    "mofina",
    "merencória",
    "prostrada",
    "comovente",
    "comovedor",
    "emocionante",
    "tocante",
    "emotivo",
    "emocional",
    "enternecedor",
    "sentido",
    "pungente",
    "dramático",
    "impressionante",
    "comovedora",
    "emotiva",
    "enternecedora",
    "sentida",
    "dramática",
    "mau",
    "ruim",
    "péssimo",
    "lamentável",
    "lastimável",
    "deplorável",
    "desolador",
    "horrível",
    "horroroso",
    "terrível",
    "trágico",
    "miserável",
    "miserando",
    "desgraçado",
    "angustiante",
    "doloroso",
    "aflitivo",
    "cruciante",
    "insuportável",
    "inadequado",
    "inapropriado",
    "má",
    "péssima",
    "desoladora",
    "horrorosa",
    "trágica",
    "miseranda",
    "desgraçada",
    "dolorosa",
    "aflitiva",
    "inadequada",
    "inapropriada",
    "pesaroso",
    "aflito",
    "agoniado",
    "angustiado",
    "ansioso",
    "desolado",
    "desesperado",
    "preocupado",
    "nervoso",
    "apreensivo",
    "atormentado",
    "inquieto",
    "impaciente",
    "consternado",
    "desconsolado",
    "amargurado",
    "aborrecido",
    "penalizado",
    "atribulado",
    "mortificado",
    "sofrido",
    "torturado",
    "pesarosa",
    "aflita",
    "agoniada",
    "angustiada",
    "ansiosa",
    "desolada",
    "desesperada",
    "preocupada",
    "nervosa",
    "apreensiva",
    "atormentada",
    "inquieta",
    "consternada",
    "desconsolada",
    "amargurada",
    "aborrecida",
    "penalizada",
    "atribulada",
    "mortificada",
    "sofrida",
    "torturada",
    "grave",
    "árduo",
    "árdua",
    "custoso",
    "custosa",
    "pesado",
    "pesada",
    "penoso",
    "penosa",
    "funesto",
    "sombrio",
    "sinistro",
    "soturno",
    "lúgubre",
    "fúnebre",
    "macabro",
    "escuro",
    "obscuro",
    "silencioso",
    "tétrico",
    "lôbrego",
    "sepulcral",
    "tumular",
    "trevoso",
    "lutuoso",
    "funesta",
    "sombria",
    "sinistra",
    "soturna",
    "macabra",
    "escura",
    "obscura",
    "silenciosa",
    "tétrica",
    "lôbrega",
    "trevosa",
    "lutuosa",
    "insignificante",
    "irrisório",
    "ínfimo",
    "mínimo",
    "parco",
    "exíguo",
    "irrisória",
    "ínfima",
    "mínima",
    "parca",
    "exígua"
  ],
  "smug": [
    "pretensioso",
    "presumido",
    "pedante",
    "arrogante",
    "convencido",
    "metido",
    "prepotente",
    "orgulhoso",
    "vaidoso",
    "vanglorioso",
    "gabarola",
    "prosa",
    "presuntuoso",
    "petulante",
    "soberbo",
    "emproado",
    "empolado",
    "afetado",
    "snob",
    "esnobe",
    "altivo",
    "imodesto",
    "enfatuado",
    "pernóstico",
    "jactancioso",
    "jactante",
    "fátuo",
    "entufado",
    "ufano",
    "empafiado",
    "garganta",
    "opinioso",
    "espevitado",
    "insolente",
    "desdenhoso",
    "desvanecido",
    "amaneirado",
    "atrevido",
    "pretensiosa",
    "presumida",
    "convencida",
    "metida",
    "orgulhosa",
    "vaidosa",
    "vangloriosa",
    "gabarola",
    "presuntuosa",
    "soberba",
    "emproada",
    "empolada",
    "afetada",
    "altiva",
    "imodesta",
    "enfatuada",
    "pernóstica",
    "jactanciosa",
    "fátua",
    "entufada",
    "ufana",
    "empafiada",
    "opiniosa",
    "espevitada",
    "desdenhosa",
    "desvanecida",
    "amaneirada",
    "atrevida"
  ],
  "surprised": [
    "passado",
    "abalado",
    "abismado",
    "admirado",
    "assombrado",
    "atônito",
    "atordoado",
    "banzado",
    "boquiaberto",
    "chocado",
    "desconcertado",
    "espantado",
    "estarrecido",
    "estupefacto",
    "estupefato",
    "maravilhado",
    "pasmado",
    "pasmo",
    "perplexo",
    "surpreendido",
    "passada",
    "abalada",
    "abismada",
    "admirada",
    "assombrada",
    "atônita",
    "atordoada",
    "banzada",
    "boquiaberta",
    "chocada",
    "desconcertada",
    "espantada",
    "estarrecida",
    "estupefacta",
    "estupefata",
    "maravilhada",
    "pasmada",
    "pasma",
    "perplexa",
    "surpreendida"
  ],
  "thinking": [
    "refletindo",
    "meditando",
    "ponderando",
    "matutando",
    "ruminando",
    "cogitando",
    "raciocinando",
    "reflexionando",
    "pesando",
    "razoando",
    "avaliando",
    "analisando",
    "estudando",
    "aprofundando",
    "pretendendo",
    "tencionando",
    "intencionando",
    "intentando",
    "querendo",
    "desejando",
    "aspirando",
    "planejando",
    "planeando",
    "programando",
    "esperando",
    "prevendo",
    "achando",
    "supondo",
    "julgando",
    "acreditando",
    "considerando",
    "crendo",
    "calculando",
    "presumindo",
    "imaginando",
    "entendendo",
    "deduzindo",
    "conjeturando",
    "excogitando",
    "cismando",
    "lembrando",
    "recordando",
    "relembrando",
    "precisando",
    "rememorando",
    "memorando",
    "memorizando",
    "evocando",
    "cuidando",
    "olhando",
    "zelando",
    "tratando",
    "atendendo",
    "curando",
    "sarando"
  ],
  "yes": [
    "sim",
    "afirmativo",
    "positivo",
    "certo",
    "isso",
    "está bem",
    "está certo",
    "com certeza",
    "de acordo",
    "efetivamente",
    "afirmativa",
    "positiva",
    "certa",
    "está certa",
    "consentimento",
    "confirmação",
    "afirmação",
    "permissão",
    "autorização",
    "aprovação",
    "assentimento",
    "anuência",
    "aquiescência",
    "aceitação",
    "concordância",
    "acordo",
    "deferimento",
    "licença",
    "homologação",
    "amém",
    "acorda"
  ],
  "no": [
    "negativo",
    "nada",
    "neca",
    "nicles",
    "népias",
    "negativa",
    "nunca",
    "jamais",
    "de jeito nenhum",
    "de jeito algum",
    "de maneira nenhuma",
    "de maneira alguma",
    "de modo algum",
    "de modo nenhum",
    "em nenhuma circunstância",
    "em circunstância alguma",
    "em nenhum momento",
    "em momento algum",
    "em tempo nenhum",
    "em tempo algum",
    "nenhuma vez",
    "negação",
    "negativa",
    "nega",
    "negaça",
    "recusa",
    "rejeição",
    "reprova",
    "reprovação",
    "refutação",
    "recusação",
    "refusão",
    "oposição",
    "denegação",
    "desabono",
    "negamento"
  ]
}
